{
  "label": "AsperX 165W",
  "slug": "asperx-165w",
  "model": "AsperX, einziehbares USB-C-Kabel, 20.000 mAh, 165W - 72Wh (AX365)",
  "peak_port_w": "100W",
  "capacity_mah": "20.000",
  "discharge_duration": "00:51h (100W->45W)\n01:03h (60W)",
  "discharge_net_wh": "63,18Wh bei 20V 5A (88%)\n63,78Wh bei 20V 3A (89%)",
  "sustained_load": "Nein, Drop auf 65W bei 55% (34Wh, 20 Min, 50°C),\nDrop auf 45W bei 19% (56Wh, 40 Min, 53°C)\nJa (60W)",
  "charge_duration": "01:53h (65W)\n01:50h (65W)",
  "charge_power": "65W peak, Drop auf 45W bei 55% (35 Min, 41°C)",
  "charge_capacity": "78,24Wh bei 65W (109%)\n75,98Wh bei 65W (106%)",
  "passthrough": "Ja",
  "ups": "Ja",
  "ports": "1x USB-C-Kabel, 1x USB-C, 1x USB-A",
  "power_per_port": "C-Kabel:  100W OUT / 65W IN\nC1:  100W OUT / 65W IN\nA1 : 100W OUT",
  "power_distribution": "C-Kabel + C1 = 100W + 65W\n C-Kabel + A1 = 100W + 30W\nC1 + A1 = 12W + 12W\n C-Kabel + C1 + A1 = 100W + 12W + 12W",
  "fixed_pdos": "5V 3A / 9V 3A / 12V 3A / 15V 3A / 20V 5A",
  "pps_range": "5V - 21V bei 5A (C-Kabel, C1)\n5V - 21V bei 5A (C-Kabel, wenn C1 lädt)\n5V - 21V bei 3,25A (C1, wenn C-Kabel lädt)",
  "avs_range": "",
  "ufcs_range": "5V - 11V bei 5A\n11V - 21V bei 5A",
  "protocols": "UFCS (100W, alle Ports)",
  "wireless": "-",
  "weight": "513g",
  "size": "15,65 x 5,20 x 4,08 cm",
  "conclusion": "Solid budget pick under 50€ with flexible I/O but clear weaknesses at 100W sustained (runs too hot). Great for 65W or dual phone/tablet charging thanks to excellent PPS range.",
  "rating": "3,5",
  "notes": "Retractable cable hides fully. Display shows percent, wattage, cycles, temps. Aluminum housing.",
  "amazon_link": "https://amzn.to/46POq3M",
  "price": "49,99 €",
  "review_link": "https://www.reddit.com/r/ChargingSheet/comments/1mllem8/asperx_165w_20000_mah_powerbank_inkl_einziehbares/",
  "misc": "https://www.reddit.com/r/ChargingSheet/comments/1nmprs0/165w_2025000_mah_powerbanks_mit_integrierten/",
  "more_tests": "",
  "links": "",
  "cell_notes": ""
}

